{
  "version": "1.0",
  "mods": [
    {
      "id": "TOHE",
      "name": "Town of Host Enhanced",
      "author": "EnhancedNetwork",
      "description": "A host-only modpack for Among Us with enhanced features",
      "githubOwner": "EnhancedNetwork",
      "githubRepo": "TownofHost-Enhanced",
      "category": "Host Mod",
      "assetFilters": {
        "steam": {
          "patterns": ["steamitchio"],
          "exclude": ["epic"]
        },
        "epic": {
          "patterns": ["epicmsstore", "epicms"],
          "exclude": []
        },
        "dll": {
          "patterns": [".dll"],
          "exclude": ["steam", "epic"]
        }
      },
      "requiresDepot": false,
      "incompatibilities": ["TownOfUs", "TheOtherRoles", "AllTheRoles", "LaunchpadReloaded"]
    },
    {
      "id": "TownOfUs",
      "name": "Town of Us Mira",
      "author": "AU-Avengers",
      "description": "Town of Us Reactivated, but cleaner using MiraAPI with many improvements!",
      "githubOwner": "AU-Avengers",
      "githubRepo": "TOU-Mira",
      "category": "Mod",
      "assetFilters": {
        "steam": {
          "patterns": ["steam-itch"],
          "exclude": []
        },
        "epic": {
          "patterns": ["epic-msstore"],
          "exclude": []
        },
        "dll": {
          "patterns": ["MiraAPI.dll"],
          "exclude": [],
          "exactMatch": true
        }
      },
      "requiresDepot": false,
      "dependencies": [
        {
          "modId": "MiraAPI",
          "name": "MiraAPI",
          "fileName": "MiraAPI.dll",
          "githubOwner": "All-Of-Us-Mods",
          "githubRepo": "MiraAPI"
        }
      ],
      "packageType": "nested",
      "incompatibilities": ["TOHE", "TheOtherRoles", "AllTheRoles", "LaunchpadReloaded"]
    },
    {
      "id": "BetterCrewLink",
      "name": "Better CrewLink",
      "author": "OhMyGuus",
      "description": "Voice proximity chat for Among Us",
      "githubOwner": "OhMyGuus",
      "githubRepo": "BetterCrewLink",
      "category": "Utility",
      "assetFilters": {
        "default": {
          "patterns": [".zip"],
          "exclude": ["source"]
        }
      },
      "requiresDepot": false,
      "incompatibilities": []
    },
    {
      "id": "TheOtherRoles",
      "name": "The Other Roles",
      "author": "TheOtherRolesAU",
      "description": "A mod for Among Us which adds many new roles, new Settings and new Custom Hats to the game",
      "githubOwner": "TheOtherRolesAU",
      "githubRepo": "TheOtherRoles",
      "category": "Mod",
      "assetFilters": {
        "steam": {
          "patterns": ["theotherroles.zip"],
          "exclude": [],
          "exactMatch": true
        },
        "epic": {
          "patterns": ["theotherroles_msstore.zip"],
          "exclude": [],
          "exactMatch": true
        },
        "dll": {
          "patterns": ["theotherroles.dll"],
          "exclude": [],
          "exactMatch": true
        }
      },
      "requiresDepot": true,
      "incompatibilities": ["AllTheRoles", "TownOfUs", "TOHE", "LaunchpadReloaded"],
      "depotConfig": {
        "depotId": 945361,
        "manifestId": "5207443046106116882",
        "gameVersion": "v15.11.0"
      }
    },
    {
      "id": "AllTheRoles",
      "name": "All The Roles",
      "author": "Zeo666",
      "description": "A mod for Among Us which adds many new roles, modifiers, game modes, map settings, hats and more",
      "githubOwner": "Zeo666",
      "githubRepo": "AllTheRoles",
      "category": "Mod",
      "assetFilters": {
        "steam": {
          "patterns": ["x86-steam-itch", "steam-itch"],
          "exclude": []
        },
        "epic": {
          "patterns": ["x64-epic-msstore", "epic-msstore"],
          "exclude": []
        }
      },
      "requiresDepot": true,
      "incompatibilities": ["TheOtherRoles", "TownOfUs", "TOHE", "LaunchpadReloaded"],
      "depotConfig": {
        "depotId": 945361,
        "manifestId": "1110308242604365209",
        "gameVersion": "v16.0.5"
      }
    },
    {
      "id": "LaunchpadReloaded",
      "name": "Launchpad: Reloaded",
      "author": "All-Of-Us-Mods",
      "description": "A vanilla oriented fun and unique Among Us client mod",
      "githubOwner": "All-Of-Us-Mods",
      "githubRepo": "LaunchpadReloaded",
      "category": "Mod",
      "assetFilters": {
        "dll": {
          "patterns": [".dll"],
          "exclude": []
        }
      },
      "requiresDepot": false,
      "dependencies": [
        {
          "modId": "Reactor",
          "name": "Reactor",
          "fileName": "Reactor.dll",
          "githubOwner": "NuclearPowered",
          "githubRepo": "Reactor"
        },
        {
          "modId": "MiraAPI",
          "name": "MiraAPI",
          "fileName": "MiraAPI.dll",
          "githubOwner": "All-Of-Us-Mods",
          "githubRepo": "MiraAPI"
        }
      ],
      "incompatibilities": ["TOHE", "TownOfUs", "TheOtherRoles", "AllTheRoles"]
    },
    {
      "id": "Reactor",
      "name": "Reactor",
      "author": "NuclearPowered",
      "description": "Shared modding framework required by multiple mods.",
      "githubOwner": "NuclearPowered",
      "githubRepo": "Reactor",
      "category": "Dependency",
      "assetFilters": {
        "dll": {
          "patterns": ["Reactor.dll"],
          "exclude": [],
          "exactMatch": true
        }
      },
      "requiresDepot": false,
      "incompatibilities": []
    },
    {
      "id": "MiraAPI",
      "name": "Mira API",
      "author": "All-Of-Us-Mods",
      "description": "Core API used by Mira-based mods.",
      "githubOwner": "All-Of-Us-Mods",
      "githubRepo": "MiraAPI",
      "category": "Dependency",
      "assetFilters": {
        "dll": {
          "patterns": ["MiraAPI.dll"],
          "exclude": [],
          "exactMatch": true
        }
      },
      "requiresDepot": false,
      "incompatibilities": []
    },
	{
      "id": "Submerged",
      "name": "Submerged",
      "author": "SubmergedAmongUs",
      "description": "A mod for Among Us which adds a new map into the game.",
      "githubOwner": "SubmergedAmongUs",
      "githubRepo": "Submerged",
      "category": "Mod",
      "assetFilters": {
        "dll": {
          "patterns": ["Submerged.dll"],
          "exclude": [],
          "exactMatch": true
        }
      },
            "requiresDepot": false,
      "dependencies": [
        {
          "modId": "Reactor",
          "name": "Reactor",
          "fileName": "Reactor.dll",
          "githubOwner": "NuclearPowered",
          "githubRepo": "Reactor"
        }
      ],
      "incompatibilities": []
	},
	{
      "id": "StellarRolesAU",
      "name": "StellarRoles",
      "author": "Mr-Fluuff",
      "description": "A mod for Among Us which adds new Roles & Modifiers, new Settings and new Custom Cosmetics to the game.",
      "githubOwner": "Mr-Fluuff",
      "githubRepo": "StellarRolesAU",
      "category": "Mod",
      "assetFilters": {
        "default": {
          "patterns": [".zip"],
          "exclude": ["source"]
        }
      },
      "requiresDepot": false,
      "dependencies": [
        {
          "modId": "Reactor",
          "name": "Reactor",
          "fileName": "Reactor.dll",
          "githubOwner": "NuclearPowered",
          "githubRepo": "Reactor"
        }
      ],
      "incompatibilities": []
	}
  ]
}